drf_messages/__init__.py
drf_messages/admin.py
drf_messages/apps.py
drf_messages/conf.py
drf_messages/filters.py
drf_messages/models.py
drf_messages/serializers.py
drf_messages/storage.py
drf_messages/urls.py
drf_messages/views.py
drf_messages/migrations/0001_initial.py
drf_messages/migrations/0002_message_session_key.py
drf_messages/migrations/__init__.py
drf_messages-1.1.1.dist-info/LICENSE
drf_messages-1.1.1.dist-info/METADATA
drf_messages-1.1.1.dist-info/WHEEL
drf_messages-1.1.1.dist-info/top_level.txt
drf_messages-1.1.1.dist-info/RECORD
